{
    "name": [
        "I:/PROYECTOS/ESTUDIANTES/Sergio/V2/GID\\Modelo_17.gid\\Modelo_17.json"
    ], 
    "Simulations_Parameters": [
        {
            "Config_conditions(1:V-P-P),(2:V-V-P)": 1, 
            "SolverType(1:AMGCGL,2:AMGCL_NS_Solver,3:BICGSTABSolver)": 1, 
            "Time_vector": [
                0, 
                7.0
            ], 
            "AutomaticDeltaTime": false, 
            "Dt": 0.075
        }
    ], 
    "Inlet": [
        {
            "Flow_inlet(mean)": -8.505539283282103e-05, 
            "Centroid": [
                -4.5771640855642946e-05, 
                0.00013088892608241338, 
                -2.379724167711286e-16
            ], 
            "Flow_inlet(peak)": -8.505539283282103e-05, 
            "Reynolds(mean)": -1625.827834478014, 
            "Diameter": 0.01998286056657306, 
            "Reynolds(peak)": -1625.827834478014, 
            "Parabolic": true, 
            "Center Node": 368205, 
            "Total_area_inlet": 0.0003136217782787033
        }
    ], 
    "Fluid Characteristic": [
        {
            "blood_dynamic_viscosity": 0.0035, 
            "blood_kinematic_viscosity": 3.3333333333333333e-06, 
            "blood_density": 1050.0
        }
    ], 
    "Pressures": [
        {
            "Pressure Inlet": [
                [
                    1459.279148329113, 
                    -623.2573185660053, 
                    182.84446395191335, 
                    -8.743964824943001, 
                    44.593686938214574, 
                    43.28217966977614, 
                    59.771891607198754, 
                    72.3431599006851, 
                    80.44361803448028, 
                    81.48994445206702, 
                    77.47520401999158, 
                    71.2375451966832, 
                    64.61885540543703, 
                    57.84944156987348, 
                    50.43461216863368, 
                    43.13442701573106, 
                    38.96336466211037, 
                    40.086327805520206, 
                    44.59956812744504, 
                    49.79636917929223, 
                    56.07820665131647, 
                    65.01614172809141, 
                    75.09239634679356, 
                    82.66149157736766, 
                    85.00086577812435, 
                    82.14996439893605, 
                    78.05083313035516, 
                    75.71886852206065, 
                    73.3611550983284, 
                    70.41416942968603, 
                    67.60808805146881, 
                    65.79686996696195, 
                    64.69709422082771, 
                    64.1602304935618, 
                    64.85364666572211, 
                    65.11226332872447, 
                    63.04083131815321, 
                    58.46465882453205, 
                    53.37372277189574, 
                    50.54372872395329, 
                    50.64055570362738, 
                    51.84723250642251, 
                    53.660263095563515, 
                    54.88929260732708, 
                    54.45631776230308, 
                    54.502567728539134, 
                    57.30188645406476, 
                    60.94165638773513, 
                    62.88627471655071, 
                    62.73839986923103, 
                    61.28867550477393, 
                    58.899131613597014, 
                    56.12833426514978, 
                    52.96387367401408, 
                    50.69946545807157, 
                    50.16261095113243, 
                    50.86610492396047, 
                    51.70121513617774, 
                    51.93704551593194, 
                    52.03457813282361, 
                    53.129424706179755, 
                    54.172636554966324, 
                    54.10736921117561, 
                    53.665023000001376, 
                    53.79591791667982, 
                    53.73955980917275, 
                    51.300678955922265, 
                    46.23647909599077, 
                    45.440702457114334, 
                    51.68415234803234, 
                    56.27170406136988, 
                    54.546648564692525, 
                    48.4848933067118, 
                    44.41547799096948, 
                    45.497590122734394, 
                    47.6404302308331, 
                    48.60925220538159, 
                    48.46208858289215, 
                    47.028730504426115, 
                    43.99977791876355, 
                    41.91728277971082, 
                    42.46420731704054, 
                    44.187168179420574, 
                    44.31469321563655, 
                    44.51507592148981, 
                    47.14221061187253, 
                    50.85088048343093, 
                    51.97801489586298, 
                    49.92339495595838, 
                    47.93110270250475, 
                    49.180075779348336, 
                    51.646511801841136, 
                    50.47768052746716, 
                    44.76005044510588
                ]
            ], 
            "Pressure Outlet 1002": [
                0
            ], 
            "Pressure Outlet 1001": [
                [
                    0.0, 
                    0.0, 
                    0.0, 
                    0.0, 
                    0.0, 
                    0.0, 
                    0.0, 
                    0.0, 
                    0.0, 
                    0.0, 
                    0.0, 
                    0.0, 
                    0.0, 
                    0.0, 
                    0.0, 
                    0.0, 
                    0.0, 
                    0.0, 
                    0.0, 
                    0.0, 
                    0.0, 
                    0.0, 
                    0.0, 
                    0.0, 
                    0.0, 
                    0.0, 
                    0.0, 
                    0.0, 
                    0.0, 
                    0.0, 
                    0.0, 
                    0.0, 
                    0.0, 
                    0.0, 
                    0.0, 
                    0.0, 
                    0.0, 
                    0.0, 
                    0.0, 
                    0.0, 
                    0.0, 
                    0.0, 
                    0.0, 
                    0.0, 
                    0.0, 
                    0.0, 
                    0.0, 
                    0.0, 
                    0.0, 
                    0.0, 
                    0.0, 
                    0.0, 
                    0.0, 
                    0.0, 
                    0.0, 
                    0.0, 
                    0.0, 
                    0.0, 
                    0.0, 
                    0.0, 
                    0.0, 
                    0.0, 
                    0.0, 
                    0.0, 
                    0.0, 
                    0.0, 
                    0.0, 
                    0.0, 
                    0.0, 
                    0.0, 
                    0.0, 
                    0.0, 
                    0.0, 
                    0.0, 
                    0.0, 
                    0.0, 
                    0.0, 
                    0.0, 
                    0.0, 
                    0.0, 
                    0.0, 
                    0.0, 
                    0.0, 
                    0.0, 
                    0.0, 
                    0.0, 
                    0.0, 
                    0.0, 
                    0.0, 
                    0.0, 
                    0.0, 
                    0.0, 
                    0.0, 
                    0.0
                ]
            ]
        }
    ], 
    "Bifurcation: ": [
        false
    ], 
    "Time": [
        {
            "Time": [
                0.075, 
                0.15, 
                0.22499999999999998, 
                0.3, 
                0.375, 
                0.45, 
                0.525, 
                0.6, 
                0.6749999999999999, 
                0.7499999999999999, 
                0.8249999999999998, 
                0.8999999999999998, 
                0.9749999999999998, 
                1.0499999999999998, 
                1.1249999999999998, 
                1.1999999999999997, 
                1.2749999999999997, 
                1.3499999999999996, 
                1.4249999999999996, 
                1.4999999999999996, 
                1.5749999999999995, 
                1.6499999999999995, 
                1.7249999999999994, 
                1.7999999999999994, 
                1.8749999999999993, 
                1.9499999999999993, 
                2.0249999999999995, 
                2.0999999999999996, 
                2.175, 
                2.25, 
                2.325, 
                2.4000000000000004, 
                2.4750000000000005, 
                2.5500000000000007, 
                2.625000000000001, 
                2.700000000000001, 
                2.7750000000000012, 
                2.8500000000000014, 
                2.9250000000000016, 
                3.0000000000000018, 
                3.075000000000002, 
                3.150000000000002, 
                3.2250000000000023, 
                3.3000000000000025, 
                3.3750000000000027, 
                3.450000000000003, 
                3.525000000000003, 
                3.600000000000003, 
                3.6750000000000034, 
                3.7500000000000036, 
                3.8250000000000037, 
                3.900000000000004, 
                3.975000000000004, 
                4.050000000000004, 
                4.125000000000004, 
                4.200000000000005, 
                4.275000000000005, 
                4.350000000000005, 
                4.425000000000005, 
                4.500000000000005, 
                4.5750000000000055, 
                4.650000000000006, 
                4.725000000000006, 
                4.800000000000006, 
                4.875000000000006, 
                4.950000000000006, 
                5.025000000000007, 
                5.100000000000007, 
                5.175000000000007, 
                5.250000000000007, 
                5.325000000000007, 
                5.4000000000000075, 
                5.475000000000008, 
                5.550000000000008, 
                5.625000000000008, 
                5.700000000000008, 
                5.775000000000008, 
                5.8500000000000085, 
                5.925000000000009, 
                6.000000000000009, 
                6.075000000000009, 
                6.150000000000009, 
                6.225000000000009, 
                6.30000000000001, 
                6.37500000000001, 
                6.45000000000001, 
                6.52500000000001, 
                6.60000000000001, 
                6.6750000000000105, 
                6.750000000000011, 
                6.825000000000011, 
                6.900000000000011, 
                6.975000000000011, 
                7.050000000000011
            ]
        }
    ], 
    "Outlet 1001": [
        {
            "Flow_outlet(peak)": 8.508594946843767e-05, 
            "Flow_outlet(mean)": 8.498936042654486e-05, 
            "Centroid": [
                -0.00010764913986362295, 
                -1.8721689260546878e-05, 
                0.28999000000000213
            ], 
            "Reynolds(mean)": 1624.5659563007232, 
            "Diameter": 0.019982856549117495, 
            "Reynolds(peak)": 1626.4122493946263, 
            "Total_area_outlet": 0.00031362165217449224, 
            "Center Node": 1610
        }
    ], 
    "Hemodynamic Parameters_1001_ABC": [
        {
            "B": -3056404709545.3896, 
            "C": -6027181.584765576, 
            "A": 260451323.9579258
        }
    ], 
    "Flow": [
        {
            "Flow Inlet": [
                [
                    -8.505539283282103e-05, 
                    -8.505539283282103e-05, 
                    -8.505539283282103e-05, 
                    -8.505539283282103e-05, 
                    -8.505539283282103e-05, 
                    -8.505539283282103e-05, 
                    -8.505539283282103e-05, 
                    -8.505539283282103e-05, 
                    -8.505539283282103e-05, 
                    -8.505539283282103e-05, 
                    -8.505539283282103e-05, 
                    -8.505539283282103e-05, 
                    -8.505539283282103e-05, 
                    -8.505539283282103e-05, 
                    -8.505539283282103e-05, 
                    -8.505539283282103e-05, 
                    -8.505539283282103e-05, 
                    -8.505539283282103e-05, 
                    -8.505539283282103e-05, 
                    -8.505539283282103e-05, 
                    -8.505539283282103e-05, 
                    -8.505539283282103e-05, 
                    -8.505539283282103e-05, 
                    -8.505539283282103e-05, 
                    -8.505539283282103e-05, 
                    -8.505539283282103e-05, 
                    -8.505539283282103e-05, 
                    -8.505539283282103e-05, 
                    -8.505539283282103e-05, 
                    -8.505539283282103e-05, 
                    -8.505539283282103e-05, 
                    -8.505539283282103e-05, 
                    -8.505539283282103e-05, 
                    -8.505539283282103e-05, 
                    -8.505539283282103e-05, 
                    -8.505539283282103e-05, 
                    -8.505539283282103e-05, 
                    -8.505539283282103e-05, 
                    -8.505539283282103e-05, 
                    -8.505539283282103e-05, 
                    -8.505539283282103e-05, 
                    -8.505539283282103e-05, 
                    -8.505539283282103e-05, 
                    -8.505539283282103e-05, 
                    -8.505539283282103e-05, 
                    -8.505539283282103e-05, 
                    -8.505539283282103e-05, 
                    -8.505539283282103e-05, 
                    -8.505539283282103e-05, 
                    -8.505539283282103e-05, 
                    -8.505539283282103e-05, 
                    -8.505539283282103e-05, 
                    -8.505539283282103e-05, 
                    -8.505539283282103e-05, 
                    -8.505539283282103e-05, 
                    -8.505539283282103e-05, 
                    -8.505539283282103e-05, 
                    -8.505539283282103e-05, 
                    -8.505539283282103e-05, 
                    -8.505539283282103e-05, 
                    -8.505539283282103e-05, 
                    -8.505539283282103e-05, 
                    -8.505539283282103e-05, 
                    -8.505539283282103e-05, 
                    -8.505539283282103e-05, 
                    -8.505539283282103e-05, 
                    -8.505539283282103e-05, 
                    -8.505539283282103e-05, 
                    -8.505539283282103e-05, 
                    -8.505539283282103e-05, 
                    -8.505539283282103e-05, 
                    -8.505539283282103e-05, 
                    -8.505539283282103e-05, 
                    -8.505539283282103e-05, 
                    -8.505539283282103e-05, 
                    -8.505539283282103e-05, 
                    -8.505539283282103e-05, 
                    -8.505539283282103e-05, 
                    -8.505539283282103e-05, 
                    -8.505539283282103e-05, 
                    -8.505539283282103e-05, 
                    -8.505539283282103e-05, 
                    -8.505539283282103e-05, 
                    -8.505539283282103e-05, 
                    -8.505539283282103e-05, 
                    -8.505539283282103e-05, 
                    -8.505539283282103e-05, 
                    -8.505539283282103e-05, 
                    -8.505539283282103e-05, 
                    -8.505539283282103e-05, 
                    -8.505539283282103e-05, 
                    -8.505539283282103e-05, 
                    -8.505539283282103e-05, 
                    -8.505539283282103e-05
                ]
            ], 
            "Flow Outlet 1002": [
                0
            ], 
            "Flow Outlet 1001": [
                [
                    8.360766943573935e-05, 
                    8.508594946843767e-05, 
                    8.499268868466723e-05, 
                    8.501356326623297e-05, 
                    8.500954369919737e-05, 
                    8.50136118371117e-05, 
                    8.501439250000855e-05, 
                    8.501533779068092e-05, 
                    8.50155867318499e-05, 
                    8.501556949521818e-05, 
                    8.501541858513576e-05, 
                    8.501523336730837e-05, 
                    8.501509406776947e-05, 
                    8.501505039970759e-05, 
                    8.501500466603087e-05, 
                    8.501502246233197e-05, 
                    8.501508724057105e-05, 
                    8.50152337412905e-05, 
                    8.501560328929707e-05, 
                    8.501632988880807e-05, 
                    8.501757228176686e-05, 
                    8.50190236493575e-05, 
                    8.50196511389349e-05, 
                    8.501839501147431e-05, 
                    8.50125375736333e-05, 
                    8.499577975790371e-05, 
                    8.497156122283457e-05, 
                    8.495232038472172e-05, 
                    8.494295173977773e-05, 
                    8.494243108240052e-05, 
                    8.494477492950486e-05, 
                    8.495105922649886e-05, 
                    8.496134844105668e-05, 
                    8.497752244089783e-05, 
                    8.498261429768316e-05, 
                    8.499060298054189e-05, 
                    8.500404961562246e-05, 
                    8.500970152095318e-05, 
                    8.500399115355285e-05, 
                    8.500003905599618e-05, 
                    8.500189538807774e-05, 
                    8.500687990825453e-05, 
                    8.501368429401908e-05, 
                    8.501587388800341e-05, 
                    8.501300022165403e-05, 
                    8.501038539020663e-05, 
                    8.500759521357533e-05, 
                    8.500226802533679e-05, 
                    8.499460523291529e-05, 
                    8.499020737493276e-05, 
                    8.499229350516694e-05, 
                    8.499120745309499e-05, 
                    8.499024585606393e-05, 
                    8.49937229570049e-05, 
                    8.499403510994485e-05, 
                    8.49977150322054e-05, 
                    8.50077525308088e-05, 
                    8.501803401243735e-05, 
                    8.501944171805965e-05, 
                    8.501398103973647e-05, 
                    8.500802458571966e-05, 
                    8.500288292084091e-05, 
                    8.50031330667197e-05, 
                    8.50065979840035e-05, 
                    8.50086540500701e-05, 
                    8.500910220926293e-05, 
                    8.500696407851672e-05, 
                    8.50026641268976e-05, 
                    8.500237631422156e-05, 
                    8.500683838400105e-05, 
                    8.500853028092312e-05, 
                    8.500819373370105e-05, 
                    8.501048958033501e-05, 
                    8.501288668633099e-05, 
                    8.50099579024231e-05, 
                    8.500360073822665e-05, 
                    8.499865451340706e-05, 
                    8.500140475159514e-05, 
                    8.501187706467759e-05, 
                    8.501886970833231e-05, 
                    8.501419389007997e-05, 
                    8.500768225805755e-05, 
                    8.500560463626996e-05, 
                    8.500506476632359e-05, 
                    8.500770221225982e-05, 
                    8.501206978145502e-05, 
                    8.5012818346058e-05, 
                    8.501121890408838e-05, 
                    8.500909070626086e-05, 
                    8.500937179141314e-05, 
                    8.500948055415608e-05, 
                    8.500763775664548e-05, 
                    8.500794352386826e-05, 
                    8.500855601406892e-05
                ]
            ]
        }
    ], 
    "Hemodynamic Parameters_1001_AB": [
        {
            "B": 3199759858502.0986, 
            "A": -272636779.8881992
        }
    ]
}